evolutionary_forest/__init__.py
evolutionary_forest/classifier.py
evolutionary_forest/feature_engineering.py
evolutionary_forest/forest.py
evolutionary_forest/learners.py
evolutionary_forest/multigene_gp.py
evolutionary_forest/preprocess_utils.py
evolutionary_forest/probability_gp.py
evolutionary_forest/sklearn_utils.py
evolutionary_forest/utils.py
evolutionary_forest/analysis/__init__.py
evolutionary_forest/analysis/posthoc_pareto_front.py
evolutionary_forest/application/__init__.py
evolutionary_forest/application/baes_class.py
evolutionary_forest/application/gp_function_test.py
evolutionary_forest/application/time_series/__init__.py
evolutionary_forest/application/time_series/tiny_step_ts.py
evolutionary_forest/component/__init__.py
evolutionary_forest/component/adaptive_crossover.py
evolutionary_forest/component/archive.py
evolutionary_forest/component/configuration.py
evolutionary_forest/component/crossover_mutation.py
evolutionary_forest/component/environmental_selection.py
evolutionary_forest/component/evaluation.py
evolutionary_forest/component/fitness.py
evolutionary_forest/component/generation.py
evolutionary_forest/component/initialization.py
evolutionary_forest/component/normalizer.py
evolutionary_forest/component/primitive_controller.py
evolutionary_forest/component/primitive_functions.py
evolutionary_forest/component/racing_selection.py
evolutionary_forest/component/random_constant.py
evolutionary_forest/component/selection.py
evolutionary_forest/component/stateful_gp.py
evolutionary_forest/component/strategy.py
evolutionary_forest/component/subset_selection.py
evolutionary_forest/component/test_function.py
evolutionary_forest/component/toolbox.py
evolutionary_forest/component/tree_utils.py
evolutionary_forest/component/archive_operators/__init__.py
evolutionary_forest/component/archive_operators/cvt_map_elites_archive.py
evolutionary_forest/component/archive_operators/greedy_selection_archive.py
evolutionary_forest-0.2.5.dist-info/AUTHORS.rst
evolutionary_forest-0.2.5.dist-info/LICENSE
evolutionary_forest-0.2.5.dist-info/METADATA
evolutionary_forest-0.2.5.dist-info/WHEEL
evolutionary_forest-0.2.5.dist-info/top_level.txt
evolutionary_forest-0.2.5.dist-info/RECORD
