Metadata-Version: 2.1
Name: evolutionary-forest
Version: 0.2.5
Summary: An open source python library for automated feature engineering based on Genetic Programming
Home-page: https://github.com/zhenlingcn/evolutionary_forest
Author: Hengzhe Zhang
Author-email: zhenlingcn@foxmail.com
License: BSD license
Keywords: evolutionary_forest
Classifier: Development Status :: 2 - Pre-Alpha
Classifier: Intended Audience :: Developers
Classifier: License :: OSI Approved :: BSD License
Classifier: Natural Language :: English
Classifier: Programming Language :: Python :: 3
Classifier: Programming Language :: Python :: 3.6
Classifier: Programming Language :: Python :: 3.7
Classifier: Programming Language :: Python :: 3.8
Requires-Python: >=3.6
License-File: LICENSE
License-File: AUTHORS.rst
Requires-Dist: scipy
Requires-Dist: hdfe
Requires-Dist: numpy
Requires-Dist: seaborn
Requires-Dist: matplotlib
Requires-Dist: deap
Requires-Dist: sympy
Requires-Dist: pandas
Requires-Dist: scikit-learn
Requires-Dist: dill
Requires-Dist: lightgbm
Requires-Dist: smt
Requires-Dist: pytest
Requires-Dist: joblib
Requires-Dist: linear-tree
Requires-Dist: mlxtend
Requires-Dist: sklearn2pmml
Requires-Dist: tpot
Requires-Dist: gplearn
Requires-Dist: scorch
Requires-Dist: umap-learn
Requires-Dist: category-encoders
